<PAMDataset>
  <PAMRasterBand band="1">
    <Histograms>
      <HistItem>
        <HistMin>-0.5</HistMin>
        <HistMax>224.5</HistMax>
        <BucketCount>225</BucketCount>
        <IncludeOutOfRange>1</IncludeOutOfRange>
        <Approximate>0</Approximate>
        <HistCounts>0|0|0|0|0|0|0|0|0|0|0|0|0|0|0|0|0|0|0|0|0|0|0|0|0|0|0|0|0|14|60|192|379|795|984|1309|1428|1614|1612|1449|1470|1470|1539|1610|1604|1716|1910|2127|2257|2416|2558|2935|3387|3589|3971|4540|4811|5775|6332|6616|7708|7750|7804|7995|7861|8181|7361|7519|7168|7038|6610|6486|6178|6326|6089|5958|5983|5567|5947|5758|5696|5732|5391|5791|5487|5928|6052|5702|5813|6063|6038|6014|6065|6073|6307|6063|5921|5870|5895|5892|6245|6165|5983|6233|6051|6491|6492|6745|6501|6386|6750|6828|8086|9493|10758|11460|11840|11621|11096|11017|10313|11805|10463|8527|8097|8012|9229|9341|7350|6417|6203|6257|6141|6262|6146|6179|6226|5990|6153|6228|5914|5829|5768|5483|5279|5178|5047|4911|5155|5005|4931|4803|4693|4643|4716|4479|4522|4337|4353|4589|4397|4475|4391|4603|4704|4661|4938|5196|5839|6359|7105|7764|8602|9731|10594|11500|12402|12521|12767|12849|12729|12207|11331|10521|9342|8586|7959|7417|7197|7597|8723|9865|11021|11459|10912|7930|4565|2094|1077|681|492|450|419|323|234|207|187|126|70|36|24|14|27|58|148|48|19|17|25|17|9|1|1|0|1</HistCounts>
      </HistItem>
    </Histograms>
    <Metadata>
      <MDI key="STATISTICS_COUNT">1062328.000000</MDI>
      <MDI key="STATISTICS_COVARIANCES">1989.522868957989,1589.907131577035,1398.170159861267,614.4950863385328</MDI>
      <MDI key="STATISTICS_EXCLUDEDVALUES"></MDI>
      <MDI key="STATISTICS_MAXIMUM">224</MDI>
      <MDI key="STATISTICS_MEAN">125.9895870202</MDI>
      <MDI key="STATISTICS_MEDIAN">124.000000</MDI>
      <MDI key="STATISTICS_MINIMUM">29</MDI>
      <MDI key="STATISTICS_SKIPFACTORX">1</MDI>
      <MDI key="STATISTICS_SKIPFACTORY">1</MDI>
      <MDI key="STATISTICS_STDDEV">44.604067852136</MDI>
    </Metadata>
  </PAMRasterBand>
  <PAMRasterBand band="2">
    <Histograms>
      <HistItem>
        <HistMin>-0.5</HistMin>
        <HistMax>226.5</HistMax>
        <BucketCount>227</BucketCount>
        <IncludeOutOfRange>1</IncludeOutOfRange>
        <Approximate>0</Approximate>
        <HistCounts>0|0|0|0|0|0|0|0|0|0|0|0|0|0|0|0|0|0|0|0|0|0|0|0|0|0|0|0|0|0|0|0|0|0|0|0|1|38|95|238|497|754|1109|1364|1618|1473|1461|1610|1554|1449|1425|1653|1596|1584|1667|1794|2103|2022|2075|2417|2420|2631|3116|3033|3315|3739|3989|4361|4886|5256|5667|6165|6383|7086|7521|7695|8030|8354|8349|8247|8207|8235|8148|8231|7859|7872|7782|7663|7539|7226|7240|7157|7121|7150|7093|7238|7255|7460|7604|7738|8019|7802|8440|8576|8568|9205|9281|9047|9120|9721|9753|9950|10167|10020|10124|10554|10267|10779|12049|13947|15504|17448|18346|16347|15625|16914|13724|12940|13615|10029|8967|8817|8104|7928|7553|7272|6906|6460|6465|6115|5877|5819|5445|5286|5275|5034|4992|4850|4629|4380|4398|4303|4373|4224|4238|4186|4438|4894|5072|5868|6538|7296|8170|9163|10087|10885|11680|12661|12539|12002|11354|10361|9673|8843|7960|7315|6886|6761|6869|7287|8011|8800|9582|9655|9116|7224|4866|2460|1381|969|764|536|429|380|309|221|169|161|151|127|123|105|65|44|48|57|55|36|24|19|21|13|17|24|32|151|75|21|19|14|8|5|1|0|1|1|1</HistCounts>
      </HistItem>
    </Histograms>
    <Metadata>
      <MDI key="STATISTICS_COUNT">1062328.000000</MDI>
      <MDI key="STATISTICS_COVARIANCES">1589.907131577035,1320.264497022013,1146.940573125697,558.3809648638146</MDI>
      <MDI key="STATISTICS_EXCLUDEDVALUES"></MDI>
      <MDI key="STATISTICS_MAXIMUM">226</MDI>
      <MDI key="STATISTICS_MEAN">123.51006751211</MDI>
      <MDI key="STATISTICS_MEDIAN">122.000000</MDI>
      <MDI key="STATISTICS_MINIMUM">36</MDI>
      <MDI key="STATISTICS_SKIPFACTORX">1</MDI>
      <MDI key="STATISTICS_SKIPFACTORY">1</MDI>
      <MDI key="STATISTICS_STDDEV">36.33544408731</MDI>
    </Metadata>
  </PAMRasterBand>
  <PAMRasterBand band="3">
    <Histograms>
      <HistItem>
        <HistMin>-0.5</HistMin>
        <HistMax>223.5</HistMax>
        <BucketCount>224</BucketCount>
        <IncludeOutOfRange>1</IncludeOutOfRange>
        <Approximate>0</Approximate>
        <HistCounts>0|0|0|0|0|0|0|0|0|0|0|0|0|0|0|0|0|0|0|0|0|0|0|0|0|0|0|0|0|0|0|0|0|0|0|0|0|0|0|0|0|0|0|0|0|0|3|61|480|907|1582|2262|3432|3496|3685|3963|4492|4845|4911|5968|7340|8048|10869|11508|15171|16416|16196|17867|16026|14816|13909|12375|12098|11170|11038|11970|10428|11278|11555|10300|11630|11086|10416|10939|11084|11063|10825|10712|11048|10655|11371|13438|15187|17112|18599|17106|16426|17999|16281|15408|16214|16057|12058|12013|10805|11291|11052|10558|9104|9296|8771|8174|7745|7566|7281|6733|6496|6444|5679|5771|5528|4956|4812|4562|4307|4040|4030|4285|3807|3773|3627|3712|3772|3901|3896|3981|4372|4857|5549|5570|6713|7217|8065|8573|8977|9769|10049|9784|9627|9192|9337|8399|8066|7534|6769|6325|6237|6146|5904|6419|6626|7364|7598|8148|8343|7972|6693|5125|3177|1697|840|496|339|337|283|253|242|219|173|174|154|138|133|89|78|66|48|40|35|34|28|33|38|37|75|53|53|50|37|55|42|44|27|22|9|23|18|12|17|10|25|25|37|138|65|24|7|4|3|2|3|0|0|1</HistCounts>
      </HistItem>
    </Histograms>
    <Metadata>
      <MDI key="STATISTICS_COUNT">1062328.000000</MDI>
      <MDI key="STATISTICS_COVARIANCES">1398.170159861267,1146.940573125697,1046.200268578165,466.246703224386</MDI>
      <MDI key="STATISTICS_EXCLUDEDVALUES"></MDI>
      <MDI key="STATISTICS_MAXIMUM">223</MDI>
      <MDI key="STATISTICS_MEAN">104.00311109187</MDI>
      <MDI key="STATISTICS_MEDIAN">98.000000</MDI>
      <MDI key="STATISTICS_MINIMUM">46</MDI>
      <MDI key="STATISTICS_SKIPFACTORX">1</MDI>
      <MDI key="STATISTICS_SKIPFACTORY">1</MDI>
      <MDI key="STATISTICS_STDDEV">32.345019223648</MDI>
    </Metadata>
  </PAMRasterBand>
  <PAMRasterBand band="4">
    <Histograms>
      <HistItem>
        <HistMin>-0.5</HistMin>
        <HistMax>218.5</HistMax>
        <BucketCount>219</BucketCount>
        <IncludeOutOfRange>1</IncludeOutOfRange>
        <Approximate>0</Approximate>
        <HistCounts>0|0|0|0|0|0|0|0|0|0|0|0|3|63|398|733|818|804|760|684|545|450|465|400|331|381|1686|4886|14719|13208|11545|6252|2573|2196|1230|1345|911|989|656|705|516|432|578|452|462|432|390|511|406|465|490|401|583|398|608|477|584|612|548|774|558|767|596|693|619|704|784|719|834|808|758|942|738|1011|905|929|1019|794|1048|1063|873|1044|1158|988|1039|1172|1160|1070|1188|1222|1164|1188|1273|1322|1328|1348|1424|1418|1499|1487|1446|1471|1618|1583|1858|1704|1620|1929|1768|1810|2016|1971|2257|2077|2133|2411|2333|2264|2677|2669|2614|2743|2835|2950|3252|3330|3327|3500|3754|4009|3901|4536|4269|4991|4911|4960|5493|5888|5620|6510|6756|6708|7311|7783|7981|8573|8663|9001|9137|9380|9668|9990|10686|10977|11101|11599|11702|12074|12552|12462|12315|12895|13024|12951|12964|13327|13279|13996|14321|14238|15417|15584|16615|18008|20026|20987|23056|25230|25341|25526|24589|23278|21990|20151|20374|21872|22478|19696|15411|10669|8553|7536|7149|6783|6502|6102|5902|5860|5124|4874|4392|3787|3293|2677|2125|1534|1070|689|464|309|165|102|37|39|18|9|2|1|1</HistCounts>
      </HistItem>
    </Histograms>
    <Metadata>
      <MDI key="STATISTICS_COUNT">1062328.000000</MDI>
      <MDI key="STATISTICS_COVARIANCES">614.4950863385328,558.3809648638146,466.246703224386,1875.64002910709</MDI>
      <MDI key="STATISTICS_EXCLUDEDVALUES"></MDI>
      <MDI key="STATISTICS_MAXIMUM">218</MDI>
      <MDI key="STATISTICS_MEAN">152.44644591877</MDI>
      <MDI key="STATISTICS_MEDIAN">167.000000</MDI>
      <MDI key="STATISTICS_MINIMUM">12</MDI>
      <MDI key="STATISTICS_SKIPFACTORX">1</MDI>
      <MDI key="STATISTICS_SKIPFACTORY">1</MDI>
      <MDI key="STATISTICS_STDDEV">43.308659978197</MDI>
    </Metadata>
  </PAMRasterBand>
</PAMDataset>
